hsla
