Metadata-Version: 1.1
Name: Glueball-hsla
Version: 1.1.2
Summary: HSLA color naming system for use in CSS generators
Home-page: http://pypi.python.org/pypi/glueball-hsla
Author: Roy Prins
Author-email: prinsroy@gmail.com
License: MIT
Platform: UNKNOWN
Classifier: Development Status :: 5 - Production/Stable
Classifier: Environment :: Console
Classifier: Intended Audience :: Developers
Classifier: Intended Audience :: Information Technology
Classifier: License :: OSI Approved :: MIT License
Classifier: Operating System :: OS Independent
Classifier: Programming Language :: Python
